easyinstruct/__init__.py
easyinstruct/engines/__init__.py
easyinstruct/engines/base_engine.py
easyinstruct/engines/chatglm2_engine.py
easyinstruct/engines/llama2_engine.py
easyinstruct/generators/__init__.py
easyinstruct/generators/backtranslation_generator.py
easyinstruct/generators/base_generator.py
easyinstruct/generators/evol_instruct_generator.py
easyinstruct/generators/kg2instruct_generator.py
easyinstruct/generators/oceangpt_generator.py
easyinstruct/generators/self_instruct_generator.py
easyinstruct/generators/kg2instruction/__init__.py
easyinstruct/generators/kg2instruction/clean_html.py
easyinstruct/generators/kg2instruction/find_rel.py
easyinstruct/generators/kg2instruction/hanlp_ner.py
easyinstruct/generators/kg2instruction/match_qid.py
easyinstruct/generators/kg2instruction/merge_ner.py
easyinstruct/generators/kg2instruction/parse_wikipedia.py
easyinstruct/generators/kg2instruction/pipeline.py
easyinstruct/generators/kg2instruction/process_html.py
easyinstruct/generators/kg2instruction/render.py
easyinstruct/generators/kg2instruction/util.py
easyinstruct/prompts/__init__.py
easyinstruct/prompts/base_prompt.py
easyinstruct/prompts/batch_prompt.py
easyinstruct/prompts/cot_prompt.py
easyinstruct/prompts/icl_prompt.py
easyinstruct/prompts/ie_prompt.py
easyinstruct/prompts/mm_prompt.py
easyinstruct/selectors/__init__.py
easyinstruct/selectors/base_selector.py
easyinstruct/selectors/code_selector.py
easyinstruct/selectors/deduplicator.py
easyinstruct/selectors/gpt_score_selector.py
easyinstruct/selectors/length_selector.py
easyinstruct/selectors/mtld_selector.py
easyinstruct/selectors/multi_selector.py
easyinstruct/selectors/ppl_selector.py
easyinstruct/selectors/random_selector.py
easyinstruct/selectors/rouge_selector.py
easyinstruct/utils/__init__.py
easyinstruct/utils/api.py
easyinstruct/utils/log.py
easyinstruct-0.1.2.dist-info/LICENSE
easyinstruct-0.1.2.dist-info/METADATA
easyinstruct-0.1.2.dist-info/WHEEL
easyinstruct-0.1.2.dist-info/top_level.txt
easyinstruct-0.1.2.dist-info/RECORD
