Metadata-Version: 2.1
Name: easyinstruct
Version: 0.1.2
Summary: An Easy-to-use Instruction Processing Framework for Large Language Models.
Home-page: https://github.com/zjunlp/EasyInstruct
Author: Yixin Ou
Keywords: AI,NLP,instruction,language model
Classifier: Programming Language :: Python :: 3.7
Classifier: Programming Language :: Python :: 3.8
Classifier: Programming Language :: Python :: 3.9
Classifier: Programming Language :: Python :: 3.10
Classifier: Programming Language :: Python :: 3.11
Classifier: Intended Audience :: Developers
Classifier: Intended Audience :: Education
Classifier: Intended Audience :: Science/Research
Requires-Python: >=3.7.0
License-File: LICENSE
Requires-Dist: torch >=1.13.0
Requires-Dist: torchvision >=0.15.0
Requires-Dist: transformers >=4.28.0
Requires-Dist: accelerate >=0.20.3
Requires-Dist: openai ==1.9.0
Requires-Dist: anthropic >=0.3.0
Requires-Dist: cohere >=4.19.0
Requires-Dist: hanlp
Requires-Dist: zhconv ==1.4.3
Requires-Dist: beautifulsoup4 ==4.11.2
Requires-Dist: bs4 ==0.0.1
Requires-Dist: lxml ==4.9.2
Requires-Dist: sqlitedict ==2.1.0
Requires-Dist: Pillow
Requires-Dist: tiktoken
Requires-Dist: nltk
Requires-Dist: rouge-score
Requires-Dist: matplotlib
Requires-Dist: scikit-learn
Requires-Dist: lexicalrichness
Requires-Dist: pandarallel
